Metadata-Version: 2.1
Name: opcua
Version: 0.95.2
Summary: Pure Python OPC-UA client and server library
Home-page: http://freeopcua.github.io/
Author: Olivier Roulet-Dubonnet
Author-email: olivier.roulet@gmail.com
License: GNU Lesser General Public License v3 or later
Platform: UNKNOWN
Classifier: Programming Language :: Python
Classifier: Programming Language :: Python :: 3
Classifier: Programming Language :: Python :: 2
Classifier: Development Status :: 4 - Beta
Classifier: Intended Audience :: Developers
Classifier: Operating System :: OS Independent
Classifier: License :: OSI Approved :: GNU Lesser General Public License v3 or later (LGPLv3+)
Classifier: Topic :: Software Development :: Libraries :: Python Modules
Provides: opcua
Provides-Extra: encryption
